pytest_azure_devops.py
pytest_azure_devops-0.3.0.dist-info/licenses/LICENSE
pytest_azure_devops-0.3.0.dist-info/METADATA
pytest_azure_devops-0.3.0.dist-info/WHEEL
pytest_azure_devops-0.3.0.dist-info/entry_points.txt
pytest_azure_devops-0.3.0.dist-info/top_level.txt
pytest_azure_devops-0.3.0.dist-info/RECORD
